lbc/__init__.py
lbc/client.py
lbc/exceptions.py
lbc/utils.py
lbc/mixin/__init__.py
lbc/mixin/ad.py
lbc/mixin/search.py
lbc/mixin/session.py
lbc/mixin/user.py
lbc/model/__init__.py
lbc/model/ad.py
lbc/model/city.py
lbc/model/enums.py
lbc/model/proxy.py
lbc/model/search.py
lbc/model/user.py
lbc-1.1.1.dist-info/METADATA
lbc-1.1.1.dist-info/WHEEL
lbc-1.1.1.dist-info/licenses/LICENSE
lbc-1.1.1.dist-info/RECORD
