Metadata-Version: 2.4
Name: lbc
Version: 1.1.1
Summary: Unofficial client for Leboncoin API
Project-URL: Homepage, https://github.com/etienne-hd/lbc
Project-URL: Repository, https://github.com/etienne-hd/lbc
Project-URL: Changelog, https://github.com/etienne-hd/lbc/blob/main/CHANGELOG.md
Author-email: Etienne HODE <hode.etienne@gmail.com>
Maintainer-email: Etienne HODE <hode.etienne@gmail.com>
License: MIT
License-File: LICENSE
Keywords: api,lbc,leboncoin,wrapper
Requires-Python: >=3.9
Requires-Dist: curl-cffi==0.11.3
